{"props": {"pageProps": {"allStacks": [{"_id": "62431d905695a66c21971216", "companyName": "Instagram", "description": "Instagram is an American photo and video sharing social networking service created by Kevin Systrom and Mike Krieger. In April 2012, Meta acquired the service for approximately US$1 billion in cash and stock", "url": "Instagram.com", "slug": "instagram", "stages": "Approved", "companyLogo": "null", "members": [], "linkedinProfile": "null", "twitterProfile": "null", "instagramProfile": "null", "verified": false, "updatedAt": "2022-04-28T07:26:46.287Z", "createdAt": "2021-09-27T07:58:03.591Z", "__v": 0, "organizationId": "62431de75695a66c2197402e"}, {"_id": "62431d905695a66c21971217", "companyName": "Samsung", "description": "Samsung is a South Korean multinational electronics company headquartered in the Yeongtong District of Suwon.", "url": "Samsung.com", "slug": "samsung", "stages": "Approved", "companyLogo": "null", "members": [], "linkedinProfile": null, "twitterProfile": null, "instagramProfile": null, "verified": false, "updatedAt": "2022-04-28T07:26:46.287Z", "createdAt": "2021-09-27T07:58:03.531Z", "__v": 0, "organizationId": "62431de75695a66c2197402f"}, {"_id": "62431d905695a66c21971218", "companyName": "Instacart", "description": "Instacart is an American company that operates a grocery delivery and pick-up service in the United States and Canada. The company offers its services via a website and mobile app. The service allows customers to order groceries from participating retailers with the shopping being done by a personal shopper.", "url": "Instacart.com", "slug": "instacart", "stages": "Approved", "companyLogo": "https://media.graphcms.com/ae4NojwSQY2U1UTbxjvb", "members": [], "linkedinProfile": null, "twitterProfile": null, "instagramProfile": null, "verified": false, "updatedAt": "2022-04-28T07:26:46.287Z", "createdAt": "2021-09-27T07:58:03.494Z", "__v": 0, "organizationId": "62431de75695a66c21974030"}, {"_id": "62431d905695a66c21971219", "companyName": "Amazon", "description": "Amazon.com, Inc. is an American multinational technology company which focuses on e-commerce, cloud computing, digital streaming, and artificial intelligence. It is one of the Big Five companies in the U.S. information technology industry, along with Google, Apple, Microsoft, and Facebook.", "url": "Amazon.in", "slug": "amazon", "stages": "Approved", "companyLogo": "null", "members": [], "linkedinProfile": null, "twitterProfile": null, "instagramProfile": null, "verified": false, "updatedAt": "2022-04-28T07:26:46.287Z", "createdAt": "2021-09-27T07:58:04.914Z", "__v": 0, "organizationId": "62431de75695a66c21974031"}], "dataStack": [{"group": "Data Modelling and Transformation", "children": [{"catetory": "Data Modelling and Transformation", "company": {"_id": "62431d925695a66c21971383", "companyName": "dbt", "companyLogo": "https://media.graphcms.com/oANfS4GBSoeJvEQMfbtF", "slug": "dbt", "url": "https://www.getdbt.com/", "categories": [{"_id": "62431d905695a66c219712eb", "name": "Data Modelling and Transformation"}]}}, {"catetory": "Data Modelling and Transformation", "company": {"_id": "62431d925695a66c219714d9", "companyName": "AWS Athena", "companyLogo": "https://media.graphcms.com/Aw9RoVRsTGmSAPuqjHPu", "slug": "aws-athena", "url": "https://aws.amazon.com/athena/", "categories": [{"_id": "62431d905695a66c219712eb", "name": "Data Modelling and Transformation"}]}}]}, {"group": "Business Intelligence (BI)", "children": [{"catetory": "Business Intelligence (BI)", "company": {"_id": "62431d925695a66c219713f1", "companyName": "Looker", "companyLogo": "https://media.graphassets.com/PTyuGgoEQGCRSUlKwQaO", "slug": "looker", "url": "https://looker.com/", "categories": [{"_id": "62431d905695a66c219712f0", "name": "Business Intelligence (BI)"}]}}]}, {"group": "Data Warehouses", "children": [{"catetory": "Data Warehouses", "company": {"_id": "62431d925695a66c21971316", "companyName": "Redshift", "companyLogo": "https://media.graphcms.com/bgiGQ1yiQDeatmScrZj6", "slug": "redshift", "url": "https://aws.amazon.com/", "categories": [{"_id": "62431d905695a66c219712ec", "name": "Data Warehouses"}]}}]}, {"group": "Workflow Orchestration", "children": [{"catetory": "Workflow Orchestration", "company": {"_id": "62431d925695a66c219713dd", "companyName": "Airflow", "companyLogo": "https://cwiki.apache.org/confluence/download/attachments/145723561/airflow_transparent.png?api=v2", "slug": "airflow", "url": "https://airflow.apache.org/", "categories": [{"_id": "62431d905695a66c219712fa", "name": "Workflow Orchestration"}]}}, {"catetory": "Workflow Orchestration", "company": {"_id": "62431d925695a66c21971373", "companyName": "Astronomer", "companyLogo": "https://media.graphcms.com/5eFbzfgR1StPBLnokJxw", "slug": "astronomer", "url": "https://www.astronomer.io/", "categories": [{"_id": "62431d905695a66c219712fa", "name": "Workflow Orchestration"}]}}]}, {"group": "Customer Data Platform(CDP)", "children": [{"catetory": "Customer Data Platform(CDP)", "company": {"_id": "62431d925695a66c21971331", "companyName": "Segment", "companyLogo": "https://media.graphassets.com/ZYqNOo1hTVy0djlkIgHA", "slug": "segment", "url": "https://segment.com/", "categories": [{"_id": "62431d905695a66c21971305", "name": "Customer Data Platform(CDP)"}, {"_id": "62431d905695a66c219712ee", "name": "Event Tracking"}]}}]}, {"group": "Event Tracking", "children": [{"catetory": "Event Tracking", "company": {"_id": "62431d925695a66c21971331", "companyName": "Segment", "companyLogo": "https://media.graphassets.com/ZYqNOo1hTVy0djlkIgHA", "slug": "segment", "url": "https://segment.com/", "categories": [{"_id": "62431d905695a66c21971305", "name": "Customer Data Platform(CDP)"}, {"_id": "62431d905695a66c219712ee", "name": "Event Tracking"}]}}]}, {"group": "ETL Tools", "children": [{"catetory": "ETL Tools", "company": {"_id": "62431d925695a66c2197130d", "companyName": "Funnel.io", "companyLogo": "https://media.graphcms.com/wsCaJtxASiC9wYadjoeW", "slug": "funnelio", "url": "https://funnel.io/", "categories": [{"_id": "62431d905695a66c219712e9", "name": "ETL Tools"}]}}]}, {"group": "Data Lakes", "children": [{"catetory": "Data Lakes", "company": {"_id": "62431d925695a66c2197138e", "companyName": "AWS S3", "companyLogo": "https://media.graphcms.com/EA7kU7h5Su6i4J0nXuL0", "slug": "aws-s3", "url": "https://aws.amazon.com/", "categories": [{"_id": "62431d905695a66c219712f9", "name": "Data Lakes"}]}}]}, {"group": "Feature Store", "children": [{"catetory": "Feature Store", "company": {"_id": "62431d925695a66c219713b8", "companyName": "Feast", "companyLogo": "null", "slug": "feast", "url": "https://feast.dev/", "categories": [{"_id": "62431d905695a66c219712ed", "name": "Feature Store"}]}}]}, {"group": "Data Apps", "children": [{"catetory": "Data Apps", "company": {"_id": "62431d925695a66c219714b3", "companyName": "Streamlit", "companyLogo": null, "slug": "streamlit", "url": "https://streamlit.io/", "categories": [{"_id": "62431d905695a66c21971307", "name": "Data Apps"}]}}]}, {"group": "Data Quality Monitoring", "children": [{"catetory": "Data Quality Monitoring", "company": {"_id": "62431d925695a66c219713de", "companyName": "Great Expectations", "companyLogo": "null", "slug": "great-expectations", "url": "https://greatexpectations.io/", "categories": [{"_id": "62431d905695a66c219712fd", "name": "Data Quality Monitoring"}]}}]}], "stack": {"_id": "628d1660f35bf26ba33ed7c8", "companyName": "justos", "description": "justos builds insurance products that are fairer, smarter, and more human. we offer our customers products that reward safe behavior, are easy to understand, and that get paid out faster when things don't go according to plan. we are using data science, design, and brand to disrupt a multi-billion dollar insurance industry, similar to what has been happening in retail banking over the last 10 years. ultimately, we are building a safe and fairer world. ", "url": "justos.com", "stages": "Approved", "companyLogo": "null", "linkedinProfile": "https://www.linkedin.com/company/olajustos/", "twitterProfile": "", "instagramProfile": "https://www.instagram.com/olajustos/", "facebookProfile": "https://www.facebook.com/justosbr", "userId": "628d1541f35bf26ba33ed6c2", "verified": true, "createdAt": "2022-05-24T17:31:12.248Z", "updatedAt": "2022-05-25T06:43:16.938Z", "slug": "justos", "organizationId": "628d1660f35bf26ba33ed7cb", "__v": 0, "members": [{"_id": "628d1541f35bf26ba33ed6c2", "fullName": "Antonio Molins", "imageUrl": "https://mds-bucket.us-southeast-1.linodeobjects.com/76855784.png"}, {"_id": "6295fdc873ef681a6ae7583f", "fullName": "juliana melo", "imageUrl": "https://lh3.googleusercontent.com/a/AATXAJyqv1tMoK73xaaaPE7kVvXlogitSCsJo4pGc3Bw=s96-c"}, {"_id": "6296037573ef681a6ae75cd3", "fullName": "eduardo ferr\u00e1ndez", "imageUrl": "https://lh3.googleusercontent.com/a-/AOh14Gj7mRdrwpIGFzhAsL_CkfAcGe4gDOyJxpzZSF3-=s96-c"}], "vendors": [{"_id": "62431d925695a66c21971383", "companyName": "dbt", "companyLogo": "https://media.graphcms.com/oANfS4GBSoeJvEQMfbtF", "slug": "dbt", "url": "https://www.getdbt.com/", "categories": [{"_id": "62431d905695a66c219712eb", "name": "Data Modelling and Transformation"}]}, {"_id": "62431d925695a66c219713f1", "companyName": "Looker", "companyLogo": "https://media.graphassets.com/PTyuGgoEQGCRSUlKwQaO", "slug": "looker", "url": "https://looker.com/", "categories": [{"_id": "62431d905695a66c219712f0", "name": "Business Intelligence (BI)"}]}, {"_id": "62431d925695a66c21971316", "companyName": "Redshift", "companyLogo": "https://media.graphcms.com/bgiGQ1yiQDeatmScrZj6", "slug": "redshift", "url": "https://aws.amazon.com/", "categories": [{"_id": "62431d905695a66c219712ec", "name": "Data Warehouses"}]}, {"_id": "62431d925695a66c219713dd", "companyName": "Airflow", "companyLogo": "https://cwiki.apache.org/confluence/download/attachments/145723561/airflow_transparent.png?api=v2", "slug": "airflow", "url": "https://airflow.apache.org/", "categories": [{"_id": "62431d905695a66c219712fa", "name": "Workflow Orchestration"}]}, {"_id": "62431d925695a66c21971331", "companyName": "Segment", "companyLogo": "https://media.graphassets.com/ZYqNOo1hTVy0djlkIgHA", "slug": "segment", "url": "https://segment.com/", "categories": [{"_id": "62431d905695a66c21971305", "name": "Customer Data Platform(CDP)"}, {"_id": "62431d905695a66c219712ee", "name": "Event Tracking"}]}, {"_id": "62431d925695a66c2197130d", "companyName": "Funnel.io", "companyLogo": "https://media.graphcms.com/wsCaJtxASiC9wYadjoeW", "slug": "funnelio", "url": "https://funnel.io/", "categories": [{"_id": "62431d905695a66c219712e9", "name": "ETL Tools"}]}, {"_id": "62431d925695a66c21971373", "companyName": "Astronomer", "companyLogo": "https://media.graphcms.com/5eFbzfgR1StPBLnokJxw", "slug": "astronomer", "url": "https://www.astronomer.io/", "categories": [{"_id": "62431d905695a66c219712fa", "name": "Workflow Orchestration"}]}, {"_id": "62431d925695a66c2197138e", "companyName": "AWS S3", "companyLogo": "https://media.graphcms.com/EA7kU7h5Su6i4J0nXuL0", "slug": "aws-s3", "url": "https://aws.amazon.com/", "categories": [{"_id": "62431d905695a66c219712f9", "name": "Data Lakes"}]}, {"_id": "62431d925695a66c219713b8", "companyName": "Feast", "companyLogo": "null", "slug": "feast", "url": "https://feast.dev/", "categories": [{"_id": "62431d905695a66c219712ed", "name": "Feature Store"}]}, {"_id": "62431d925695a66c219714b3", "companyName": "Streamlit", "companyLogo": null, "slug": "streamlit", "url": "https://streamlit.io/", "categories": [{"_id": "62431d905695a66c21971307", "name": "Data Apps"}]}, {"_id": "62431d925695a66c219714d9", "companyName": "AWS Athena", "companyLogo": "https://media.graphcms.com/Aw9RoVRsTGmSAPuqjHPu", "slug": "aws-athena", "url": "https://aws.amazon.com/athena/", "categories": [{"_id": "62431d905695a66c219712eb", "name": "Data Modelling and Transformation"}]}, {"_id": "62431d925695a66c219713de", "companyName": "Great Expectations", "companyLogo": "null", "slug": "great-expectations", "url": "https://greatexpectations.io/", "categories": [{"_id": "62431d905695a66c219712fd", "name": "Data Quality Monitoring"}]}]}, "stackMembers": [{"_id": "628d1541f35bf26ba33ed6c2", "fullName": "Antonio Molins", "username": "amolins", "email": "antonio@justos.com", "secondaryEmail": null, "secondaryEmailType": null, "authType": "google", "authId": "102104882398444903529", "graphCmsUser": false, "otpTimeout": "2022-05-23T09:54:37.985Z", "verified": true, "onboarding": true, "imageUrl": "https://mds-bucket.us-southeast-1.linodeobjects.com/76855784.png", "newsLetter": true, "emailExist": true, "createdAt": "2022-05-24T17:26:25.427Z", "updatedAt": "2022-05-31T17:05:50.745Z", "__v": 0}, {"_id": "6295fdc873ef681a6ae7583f", "fullName": "juliana melo", "username": "julianamelo", "email": "jmelo@justos.com", "secondaryEmail": null, "secondaryEmailType": null, "authType": "google", "authId": "106280280165804141046", "graphCmsUser": false, "otpTimeout": "2022-05-27T15:21:36.644Z", "verified": true, "onboarding": false, "imageUrl": "https://lh3.googleusercontent.com/a/AATXAJyqv1tMoK73xaaaPE7kVvXlogitSCsJo4pGc3Bw=s96-c", "newsLetter": true, "emailExist": true, "createdAt": "2022-05-31T11:36:40.596Z", "updatedAt": "2022-05-31T11:36:56.960Z", "__v": 0}, {"_id": "6296037573ef681a6ae75cd3", "fullName": "eduardo ferr\u00e1ndez", "username": "eferrandez", "email": "eferrandez@justos.com", "secondaryEmail": null, "secondaryEmailType": null, "authType": "google", "authId": "101738349821778910745", "graphCmsUser": false, "otpTimeout": "2022-05-27T15:21:36.644Z", "verified": true, "onboarding": false, "imageUrl": "https://lh3.googleusercontent.com/a-/AOh14Gj7mRdrwpIGFzhAsL_CkfAcGe4gDOyJxpzZSF3-=s96-c", "newsLetter": true, "emailExist": true, "createdAt": "2022-05-31T12:00:53.496Z", "updatedAt": "2022-05-31T12:01:00.104Z", "__v": 0}]}, "__N_SSP": true}, "page": "/stacks/[id]", "query": {"id": "justos"}, "buildId": "Ey1OgCTKITdaGAVTxPEki", "isFallback": false, "gssp": true, "scriptLoader": []}